.dada-version
MANIFEST.in
README.md
requirements.dev.txt
requirements.txt
setup.cfg
setup.py
dada/__init__.py
dada/admin.py
dada/factory.py
dada/models/__init__.py
dada/models/api_mixin.py
dada/models/api_request.py
dada/models/api_response.py
dada/models/base.py
dada/models/core.py
dada/models/desktop.py
dada/models/field.py
dada/models/file.py
dada/models/file_folder.py
dada/models/folder.py
dada/models/folder_desktop.py
dada/models/mixin.py
dada/models/tag.py
dada/models/tag_join_table.py
dada/models/theme_table.py
dada/models/user.py
dada/queue/__init__.py
dada/queue/core.py
dada/queue/dada_file.py
dada/resources/__init__.py
dada/resources/core.py
dada/resources/desktops.py
dada/resources/fields.py
dada/resources/files.py
dada/resources/folders.py
dada/resources/me.py
dada/resources/tags.py
dada/resources/users.py
dada/tests/__init__.py
dada/tests/core.py
dada/tests/dada_file/__init__.py
dada/tests/dada_file/test_dada_file.py
dada/tests/models/__init__.py
dada/tests/resources/__init__.py
dada/tests/resources/test_fields.py
dada/tests/resources/test_files.py
dada_lake.egg-info/PKG-INFO
dada_lake.egg-info/SOURCES.txt
dada_lake.egg-info/dependency_links.txt
dada_lake.egg-info/entry_points.txt
dada_lake.egg-info/requires.txt
dada_lake.egg-info/top_level.txt
scripts/__init__.py
scripts/celery_helper.py
scripts/lib-bump-versions.py
scripts/lib-dist.py
scripts/lib-install-dev.py