Metadata-Version: 1.0
Name: dada-lake
Version: 0.0.9
Summary: API and Filesystem for dada-lake
Home-page: http://globally.ltd
Author: gltd
Author-email: hey@gltd.email
License: UNKNOWN
Platform: UNKNOWN
